CHANGELOG.txt
LICENCE.txt
MANIFEST.in
README.txt
setup.cfg
setup.py
tload/__init__.py
tload.egg-info/PKG-INFO
tload.egg-info/SOURCES.txt
tload.egg-info/dependency_links.txt
tload.egg-info/requires.txt
tload.egg-info/top_level.txt